gitimport.py
setup.py
gitimport.egg-info/.DS_Store
gitimport.egg-info/PKG-INFO
gitimport.egg-info/SOURCES.txt
gitimport.egg-info/dependency_links.txt
gitimport.egg-info/requires.txt
gitimport.egg-info/top_level.txt