Metadata-Version: 1.1
Name: gitimport
Version: 1.2.0
Summary: Import python packages directly from a git repository
Home-page: https://github.com/fourplusone/gitimport
Author: Matthias Bartelmeß
Author-email: mba@fourplusone.de
License: MIT
Platform: UNKNOWN
Classifier: Development Status :: 4 - Beta
Classifier: License :: OSI Approved :: MIT License
Classifier: Programming Language :: Python :: 3.4
Classifier: Programming Language :: Python :: 3.5
Classifier: Programming Language :: Python :: 3 :: Only
